socialization/.gitignore
socialization/LICENSE
socialization/README.md
socialization/__init__.py
socialization/codes.py
socialization/bot/__init__.py
socialization/bot/base_bot.py
socialization/bot/json_socket_user.py
socialization/bot/message.py
socialization/ccs/__init__.py
socialization/ccs/base_god_service.py
socialization/ccs/base_goddess_service.py
socialization/ccs/database_agent.py
socialization/ccs/god_service.py
socialization/ccs/goddess_service.py
socialization/ccs/json_ws_active_service.py
socialization/ccs/json_ws_passive_service.py
socialization-0.0.8.dist-info/METADATA
socialization-0.0.8.dist-info/WHEEL
socialization-0.0.8.dist-info/licenses/LICENSE
socialization-0.0.8.dist-info/RECORD
